pysinfo/__init__.py
pysinfo/__main__.py
pysinfo-1.1.dist-info/licenses/LICENSE
pysinfo-1.1.dist-info/METADATA
pysinfo-1.1.dist-info/WHEEL
pysinfo-1.1.dist-info/entry_points.txt
pysinfo-1.1.dist-info/top_level.txt
pysinfo-1.1.dist-info/RECORD
