Metadata-Version: 2.4
Name: pysinfo
Version: 1.1
Summary: PySInfo: A python command line tool that displays information about the current system, including hardware and critical software.
Home-page: http://blog.cycleuser.org
Author: cycleuser
Author-email: cycleuser@cycleuser.org
License-File: LICENSE
Requires-Dist: psutil
Requires-Dist: distro
Requires-Dist: GPUtil
Requires-Dist: colorama
Dynamic: author
Dynamic: author-email
Dynamic: description
Dynamic: description-content-type
Dynamic: home-page
Dynamic: license-file
Dynamic: requires-dist
Dynamic: summary
